shiutils/__init__.py
shiutils/hello.py
shiutils-0.1.dist-info/METADATA
shiutils-0.1.dist-info/WHEEL
shiutils-0.1.dist-info/top_level.txt
shiutils-0.1.dist-info/RECORD
