Metadata-Version: 2.1
Name: shiutils
Version: 0.1
Summary: A simple utility package with a hello function
Home-page: https://github.com/yourusername/shiutils
Author: Your Name
Author-email: your.email@example.com
License: UNKNOWN
Platform: UNKNOWN
Classifier: Programming Language :: Python :: 3
Classifier: License :: OSI Approved :: MIT License
Classifier: Operating System :: OS Independent
Requires-Python: >=3.6
